Metadata-Version: 2.1
Name: odoo-addon-stock_measuring_device
Version: 18.0.1.0.0.10
Requires-Python: >=3.10
Requires-Dist: odoo-addon-component==18.0.*
Requires-Dist: odoo-addon-product_dimension==18.0.*
Requires-Dist: odoo-addon-product_packaging_dimension==18.0.*
Requires-Dist: odoo-addon-product_packaging_level==18.0.*
Requires-Dist: odoo-addon-web_notify==18.0.*
Requires-Dist: odoo-addon-web_tree_dynamic_colored_field==18.0.*
Requires-Dist: odoo==18.0.*
Summary: Implement a common interface for measuring and weighing devices
Home-page: https://github.com/OCA/stock-logistics-interfaces
License: AGPL-3
Author: Camptocamp, Odoo Community Association (OCA)
Author-email: support@odoo-community.org
Classifier: Programming Language :: Python
Classifier: Framework :: Odoo
Classifier: Framework :: Odoo :: 18.0
Classifier: License :: OSI Approved :: GNU Affero General Public License v3
Classifier: Development Status :: 3 - Alpha
